waterfurnace/__init__.py
waterfurnace/cli.py
waterfurnace/waterfurnace.py
waterfurnace-1.5.1.dist-info/licenses/LICENSE
waterfurnace-1.5.1.dist-info/METADATA
waterfurnace-1.5.1.dist-info/WHEEL
waterfurnace-1.5.1.dist-info/entry_points.txt
waterfurnace-1.5.1.dist-info/top_level.txt
waterfurnace-1.5.1.dist-info/RECORD
