Metadata-Version: 2.4
Name: waterfurnace
Version: 1.5.1
Summary: Python interface for waterfurnace geothermal systems
Home-page: https://github.com/sdague/waterfurnace
Author: Sean Dague
Author-email: sean@dague.net
License: Apache Software License 2.0
Keywords: waterfurnace
Classifier: Development Status :: 5 - Production/Stable
Classifier: Intended Audience :: Developers
Classifier: License :: OSI Approved :: Apache Software License
Classifier: Natural Language :: English
Classifier: Programming Language :: Python :: 3
Classifier: Programming Language :: Python :: 3.10
Classifier: Programming Language :: Python :: 3.11
Classifier: Programming Language :: Python :: 3.12
Classifier: Programming Language :: Python :: 3.13
Classifier: Programming Language :: Python :: 3.14
License-File: LICENSE
Requires-Dist: Click>=6.0
Requires-Dist: requests>=2.18
Requires-Dist: websocket-client>=0.47
Provides-Extra: test
Requires-Dist: pytest; extra == "test"
Dynamic: author
Dynamic: author-email
Dynamic: classifier
Dynamic: description
Dynamic: description-content-type
Dynamic: home-page
Dynamic: keywords
Dynamic: license
Dynamic: license-file
Dynamic: provides-extra
Dynamic: requires-dist
Dynamic: summary
